LICENSE
django_rediser/__init__.py
django_rediser/config.py
django_rediser/settings.py
django_rediser/storage.py
django_rediser-0.0.3.27.dist-info/LICENSE
django_rediser-0.0.3.27.dist-info/METADATA
django_rediser-0.0.3.27.dist-info/WHEEL
django_rediser-0.0.3.27.dist-info/top_level.txt
django_rediser-0.0.3.27.dist-info/RECORD
